event_interface/__init__.py
st_textnav_4/__init__.py
st_textnav_4-0.0.1.dist-info/LICENSE
st_textnav_4-0.0.1.dist-info/METADATA
st_textnav_4-0.0.1.dist-info/WHEEL
st_textnav_4-0.0.1.dist-info/top_level.txt
st_textnav_4-0.0.1.dist-info/RECORD
